tcex/__init__.py
tcex/__metadata__.py
tcex/registry.py
tcex/tcex.py
tcex/api/__init__.py
tcex/api/api.py
tcex/api/tc/__init__.py
tcex/api/tc/tc.py
tcex/api/tc/ti_transform/__init__.py
tcex/api/tc/ti_transform/ti_predefined_functions.py
tcex/api/tc/ti_transform/ti_transform.py
tcex/api/tc/ti_transform/transform_abc.py
tcex/api/tc/ti_transform/model/__init__.py
tcex/api/tc/ti_transform/model/transform_model.py
tcex/api/tc/util/__init__.py
tcex/api/tc/util/threat_intel_util.py
tcex/api/tc/v2/__init__.py
tcex/api/tc/v2/v2.py
tcex/api/tc/v2/batch/__init__.py
tcex/api/tc/v2/batch/association.py
tcex/api/tc/v2/batch/attribute.py
tcex/api/tc/v2/batch/batch.py
tcex/api/tc/v2/batch/batch_submit.py
tcex/api/tc/v2/batch/batch_writer.py
tcex/api/tc/v2/batch/group.py
tcex/api/tc/v2/batch/indicator.py
tcex/api/tc/v2/batch/security_label.py
tcex/api/tc/v2/batch/tag.py
tcex/api/tc/v2/datastore/__init__.py
tcex/api/tc/v2/datastore/cache.py
tcex/api/tc/v2/datastore/datastore.py
tcex/api/tc/v2/metric/__init__.py
tcex/api/tc/v2/metric/metric.py
tcex/api/tc/v2/notification/__init__.py
tcex/api/tc/v2/notification/notification.py
tcex/api/tc/v2/threat_intelligence/__init__.py
tcex/api/tc/v2/threat_intelligence/tcex_ti_tc_request.py
tcex/api/tc/v2/threat_intelligence/threat_intelligence.py
tcex/api/tc/v2/threat_intelligence/mapping/__init__.py
tcex/api/tc/v2/threat_intelligence/mapping/filters.py
tcex/api/tc/v2/threat_intelligence/mapping/mapping.py
tcex/api/tc/v2/threat_intelligence/mapping/owner.py
tcex/api/tc/v2/threat_intelligence/mapping/security_label.py
tcex/api/tc/v2/threat_intelligence/mapping/tag.py
tcex/api/tc/v2/threat_intelligence/mapping/tags.py
tcex/api/tc/v2/threat_intelligence/mapping/task.py
tcex/api/tc/v2/threat_intelligence/mapping/victim.py
tcex/api/tc/v2/threat_intelligence/mapping/group/__init__.py
tcex/api/tc/v2/threat_intelligence/mapping/group/group.py
tcex/api/tc/v2/threat_intelligence/mapping/group/group_type/__init__.py
tcex-4.0.9.dist-info/licenses/LICENSE
tcex-4.0.9.dist-info/METADATA
tcex-4.0.9.dist-info/WHEEL
tcex-4.0.9.dist-info/top_level.txt
tcex-4.0.9.dist-info/RECORD
